MANIFEST.in
README.md
setup.py
redditanalysis/__init__.py
redditanalysis.egg-info/PKG-INFO
redditanalysis.egg-info/SOURCES.txt
redditanalysis.egg-info/dependency_links.txt
redditanalysis.egg-info/entry_points.txt
redditanalysis.egg-info/not-zip-safe
redditanalysis.egg-info/requires.txt
redditanalysis.egg-info/top_level.txt
redditanalysis/words/common-words.txt
redditanalysis/words/dict-words.txt