Metadata-Version: 1.1
Name: redditanalysis
Version: 0.1.4
Summary: A tool to aid in the production of word clouds for subreddits and users on reddit.
Home-page: https://github.com/rhiever/reddit-analysis
Author: Randy Olson
Author-email: rso@randalolson.com
License: GPLv3
Platform: UNKNOWN
Classifier: Intended Audience :: Developers
Classifier: License :: OSI Approved :: BSD License
Classifier: Operating System :: OS Independent
Classifier: Programming Language :: Python
